{
  "events":[
    {
      "id":4,
      "name":"Event00007",
      "x":27.5,
      "y":6.5,
      "states":[
        {
          "conditions":[
            
          ],
          "sprite":{
            "name":"sys/vx_chara02_c.png",
            "spriteIndex":3,
            "dir":0,
            "step":1
          },
          "height":1,
          "affixDirection":false,
          "trigger":2,
          "animationType":2,
          "runOnceThenIncrementState":true,
          "cmds":[
            {
              "jsonClass":"ShowText",
              "lines":[
                "Olá senhor"
              ],
              "useCharacterFace":false,
              "characterId":0
            },
            {
              "jsonClass":"PlaySound",
              "spec":{
                "sound":"sys/opengameart-rpg-sound-pack/NPC/shade/shade12.ogg",
                "volume":1.0,
                "pitch":1.5
              }
            }
          ]
        },
        {
          "conditions":[
            
          ],
          "sprite":{
            "name":"sys/vx_chara02_c.png",
            "spriteIndex":3,
            "dir":0,
            "step":1
          },
          "height":1,
          "affixDirection":false,
          "trigger":1,
          "animationType":2,
          "runOnceThenIncrementState":true,
          "cmds":[
            {
              "jsonClass":"ShowText",
              "lines":[
                "O que você quer?"
              ],
              "useCharacterFace":false,
              "characterId":0
            }
          ]
        },
        {
          "conditions":[
            
          ],
          "sprite":{
            "name":"sys/vx_chara02_c.png",
            "spriteIndex":3,
            "dir":0,
            "step":1
          },
          "height":1,
          "affixDirection":false,
          "trigger":1,
          "animationType":0,
          "runOnceThenIncrementState":true,
          "cmds":[
            {
              "jsonClass":"ShowText",
              "lines":[
                "Enfrentar o monstro é muito arriscado"
              ],
              "useCharacterFace":false,
              "characterId":0
            }
          ]
        },
        {
          "conditions":[
            
          ],
          "sprite":{
            "name":"sys/vx_chara02_c.png",
            "spriteIndex":3,
            "dir":0,
            "step":1
          },
          "height":1,
          "affixDirection":false,
          "trigger":1,
          "animationType":0,
          "runOnceThenIncrementState":true,
          "cmds":[
            {
              "jsonClass":"ShowText",
              "lines":[
                "Mas se é isso que você quer..."
              ],
              "useCharacterFace":false,
              "characterId":0
            }
          ]
        },
        {
          "conditions":[
            
          ],
          "sprite":{
            "name":"sys/vx_chara02_c.png",
            "spriteIndex":3,
            "dir":0,
            "step":1
          },
          "height":1,
          "affixDirection":false,
          "trigger":1,
          "animationType":0,
          "runOnceThenIncrementState":true,
          "cmds":[
            {
              "jsonClass":"StartBattle",
              "encounterId":{
                "jsonClass":"IntParameter",
                "constant":0,
                "valueTypeId":0,
                "localVariable":"",
                "globalVariable":""
              }
            }
          ]
        },
        {
          "conditions":[
            
          ],
          "sprite":{
            "name":"sys/vx_chara02_c.png",
            "spriteIndex":3,
            "dir":0,
            "step":1
          },
          "height":1,
          "affixDirection":false,
          "trigger":1,
          "animationType":0,
          "runOnceThenIncrementState":false,
          "cmds":[
            {
              "jsonClass":"ShowText",
              "lines":[
                "Parabéns pela vitória"
              ],
              "useCharacterFace":false,
              "characterId":0
            },
            {
              "jsonClass":"ShowText",
              "lines":[
                "Vou te teletransportar para a outra saída da caverna"
              ],
              "useCharacterFace":false,
              "characterId":0
            },
            {
              "jsonClass":"Teleport",
              "loc":{
                "map":"Map000003.rpgmap",
                "x":0.5,
                "y":27.5
              },
              "transitionId":1
            }
          ]
        }
      ],
      "eventClassId":-1,
      "params":[
        
      ]
    },
    {
      "id":5,
      "name":"Event00007",
      "x":9.5,
      "y":19.5,
      "states":[
        {
          "conditions":[
            
          ],
          "sprite":{
            "name":"sys/vx_chara03_a.png",
            "spriteIndex":0,
            "dir":0,
            "step":1
          },
          "height":1,
          "affixDirection":false,
          "trigger":2,
          "animationType":2,
          "runOnceThenIncrementState":true,
          "cmds":[
            {
              "jsonClass":"ShowText",
              "lines":[
                "Gosto de morar na caverna e vender minhas mercadorias"
              ],
              "useCharacterFace":false,
              "characterId":0
            }
          ]
        }
      ],
      "eventClassId":-1,
      "params":[
        
      ]
    },
    {
      "id":6,
      "name":"Event00006",
      "x":1.5,
      "y":0.5,
      "states":[
        {
          "conditions":[
            
          ],
          "height":0,
          "affixDirection":false,
          "trigger":1,
          "animationType":0,
          "runOnceThenIncrementState":false,
          "cmds":[
            {
              "jsonClass":"Teleport",
              "loc":{
                "map":"Map000001.rpgmap",
                "x":15.5,
                "y":19.5
              },
              "transitionId":1
            }
          ]
        }
      ],
      "eventClassId":-1,
      "params":[
        
      ]
    }
  ]
}